CHANGELOG.md
model_subscription/__init__.py
model_subscription/apps.py
model_subscription/constants.py
model_subscription/decorators.py
model_subscription/mixin.py
model_subscription/models.py
model_subscription/observers.py
model_subscription/subscriber.py
model_subscription/types.py
model_subscription/utils.py
django_model_subscription-0.2.2.dist-info/LICENSE
django_model_subscription-0.2.2.dist-info/WHEEL
django_model_subscription-0.2.2.dist-info/METADATA
django_model_subscription-0.2.2.dist-info/RECORD
