Metadata-Version: 2.1
Name: django-model-subscription
Version: 0.2.2
Summary: Subscription model for a django model instance.
Home-page: https://django-model-subscription.readthedocs.io/en/latest/index.html
License: MIT
Keywords: django model subscription,model observer,model change subscriber,model subscriptions,model instance subscription
Author: Tonye Jack
Author-email: tonyejck@gmail.com
Requires-Python: >=3.6.0,<3.10.0
Classifier: Development Status :: 5 - Production/Stable
Classifier: Environment :: Web Environment
Classifier: Framework :: Django
Classifier: Framework :: Django :: 2.0
Classifier: Framework :: Django :: 2.1
Classifier: Framework :: Django :: 2.2
Classifier: Framework :: Django :: 3.0
Classifier: Framework :: Django :: 3.1
Classifier: Framework :: Django :: 3.2
Classifier: Intended Audience :: Developers
Classifier: License :: OSI Approved :: MIT License
Classifier: Operating System :: OS Independent
Classifier: Programming Language :: Python
Classifier: Programming Language :: Python :: 3
Classifier: Programming Language :: Python :: 3.6
Classifier: Programming Language :: Python :: 3.7
Classifier: Programming Language :: Python :: 3.8
Classifier: Programming Language :: Python :: 3.9
Classifier: Topic :: Internet :: WWW/HTTP
Classifier: Topic :: Internet :: WWW/HTTP :: Dynamic Content
Provides-Extra: deploy
Provides-Extra: development
Requires-Dist: django-lifecycle (>=0.9.0,<0.10.0)
Requires-Dist: six (>=1.14,<2.0)
Requires-Dist: typing (>=3.6,<4.0); python_version >= "3.4" and python_version < "3.5"
Requires-Dist: typing_extensions (>=3.7,<4.0)
Project-URL: Documentation, https://django-model-subscription.readthedocs.io/en/latest/index.html
Project-URL: Repository, https://github.com/jackton1/django-model-subscription
